{
  "version": "1.0.0",
  "issue": 311,
  "title": "Messaging — Tanstack Query hooks for offers",
  "branch": "feat/311/messaging-offer-hooks",
  "status": "implementing",
  "phase": {
    "current": 2,
    "total": 2,
    "tasks": {
      "completed": ["1.1", "1.2"],
      "current": "2.1",
      "remaining": ["2.2", "2.3"]
    }
  },
  "health": { "build": "pass", "lint": "unknown", "tests": "unknown" },
  "failureCount": { "currentTask": 0 },
  "timestamps": { "started": "2026-03-31T12:00:00Z", "lastActivity": "2026-03-31T12:05:00Z" }
}
